shelect/__init__.py
shelect/__main__.py
shelect/ast_utils.py
shelect/cli.py
shelect/engine.py
shelect/filesystem.py
shelect/filesystem_fake.py
shelect/output.py
shelect/output_fake.py
shelect/repl.py
shelect/test_ast_utils.py
shelect/test_engine.py
shelect-0.1.1.dist-info/licenses/LICENSE
shelect-0.1.1.dist-info/METADATA
shelect-0.1.1.dist-info/WHEEL
shelect-0.1.1.dist-info/entry_points.txt
shelect-0.1.1.dist-info/top_level.txt
shelect-0.1.1.dist-info/RECORD
