Metadata-Version: 2.4
Name: shelect
Version: 0.1.1
Summary: SQL for your local CSV/JSON files
Author-email: Sufian Rhazi <sufian@gmail.com>
License-Expression: MIT
Project-URL: Homepage, https://github.com/sufianrhazi/shelect
Project-URL: Issues, https://github.com/sufianrhazi/shelect/issues
Requires-Python: >=3.8
License-File: LICENSE
Requires-Dist: sqlglot>=26.12.0
Dynamic: license-file
